VoiceProcessingToolkit/VoiceProcessingManager.py
VoiceProcessingToolkit/__init__.py
VoiceProcessingToolkit/shared_resources.py
VoiceProcessingToolkit/text_to_speech/__init__.py
VoiceProcessingToolkit/text_to_speech/elevenlabs_tts.py
VoiceProcessingToolkit/transcription/__init__.py
VoiceProcessingToolkit/transcription/whisper.py
VoiceProcessingToolkit/voice_detection/Voicerecorder.py
VoiceProcessingToolkit/voice_detection/__init__.py
VoiceProcessingToolkit/wake_word_detector/ActionManager.py
VoiceProcessingToolkit/wake_word_detector/AudioStreamManager.py
VoiceProcessingToolkit/wake_word_detector/NotificationSoundManager.py
VoiceProcessingToolkit/wake_word_detector/WakeWordDetector.py
VoiceProcessingToolkit/wake_word_detector/__init__.py
VoiceProcessingToolkit/wake_word_detector/Wav_MP3/__init__.py
VoiceProcessingToolkit/wake_word_detector/Wav_MP3/notification.wav
VoiceProcessingToolkit-0.1.8.3.dist-info/LICENSE.txt
VoiceProcessingToolkit-0.1.8.3.dist-info/METADATA
VoiceProcessingToolkit-0.1.8.3.dist-info/WHEEL
VoiceProcessingToolkit-0.1.8.3.dist-info/top_level.txt
VoiceProcessingToolkit-0.1.8.3.dist-info/RECORD
