Metadata-Version: 2.1
Name: VoiceProcessingToolkit
Version: 0.1.8.3
Summary: A comprehensive library for voice processing tasks such as wake word detection, speech recognition, translation, and text-to-speech.
Home-page: https://github.com/kristofferv98/VoiceProcessingToolkit.git
Author: Kristoffer Vatnehol
Author-email: kristoffer.vatnehol@appacia.com
Project-URL: Bug Tracker, https://github.com/kristofferv98/VoiceProcessingToolkit.git
Classifier: Programming Language :: Python :: 3
Classifier: License :: OSI Approved :: MIT License
Classifier: Operating System :: OS Independent
Requires-Python: >=3.6
License-File: LICENSE.txt
Requires-Dist: PyAudio ~=0.2.14
Requires-Dist: openai <2.0.0,>=1.10.0
Requires-Dist: python-dotenv
Requires-Dist: requests ~=2.31.0
Requires-Dist: elevenlabs ==0.2.27
Requires-Dist: numpy ~=1.26.2
Requires-Dist: pvcobra ~=2.0.1
Requires-Dist: pvkoala ~=2.0.0
Requires-Dist: pvporcupine ~=3.0.1
Requires-Dist: pygame ~=2.5.2
